odoo/addons/account_invoice_comment/LICENSE
odoo/addons/account_invoice_comment/README.rst
odoo/addons/account_invoice_comment/__init__.py
odoo/addons/account_invoice_comment/__manifest__.py
odoo/addons/account_invoice_comment/i18n/de.po
odoo/addons/account_invoice_comment/images/screen.png
odoo/addons/account_invoice_comment/models/__init__.py
odoo/addons/account_invoice_comment/models/account_move.py
odoo/addons/account_invoice_comment/models/res_company.py
odoo/addons/account_invoice_comment/models/res_config_settings.py
odoo/addons/account_invoice_comment/models/sale_order.py
odoo/addons/account_invoice_comment/static/description/icon.png
odoo/addons/account_invoice_comment/static/description/index.html
odoo/addons/account_invoice_comment/tests/TEST_INSTRUCTIONS.rst
odoo/addons/account_invoice_comment/views/account.xml
odoo/addons/account_invoice_comment/views/res_config_settings_views.xml
odoo_addon_account_invoice_comment-18.0.1.0.0.dist-info/METADATA
odoo_addon_account_invoice_comment-18.0.1.0.0.dist-info/WHEEL
odoo_addon_account_invoice_comment-18.0.1.0.0.dist-info/top_level.txt
odoo_addon_account_invoice_comment-18.0.1.0.0.dist-info/RECORD
